<?xml version="1.0"?>
<openerp>
  <data>

    <record id="document_from_dms_form_view" model="ir.ui.view">
      <field name="name">Search Document</field>
      <field name="model">ir.attachment.dms.wizard</field>
      <field name="arch" type="xml">
        <form string="Search Document" version="7.0">
        <label string="This action allows you to search by file name and to add the document you select"/>
        <group string="Search Document">
          <div width="100%%">
            <field  name="name"
                    width="70%%"
                    class="oe_inline"/>
            <button name="search_doc"
                    string="Search"
                    type="object"
                    width="15%%"
                    class="oe_inline oe_highlight" />
          </div>
          <field name="attachment_ids" colspan="4" nolabel="1"/>
        </group>
        <footer>
          <button name="action_apply" string="Apply" type="object" class="oe_highlight"/>
          or
          <button special="cancel" string="Cancel" type="object" class="oe_link"/>
        </footer>
      </form>
      </field>
    </record>

  </data>
</openerp>
